cpdfkit/__init__.py
cpdfkit/cpdfkit.py
cpdfkit/exceptions.py
cpdfkit-0.1.6.dist-info/LICENSE
cpdfkit-0.1.6.dist-info/METADATA
cpdfkit-0.1.6.dist-info/WHEEL
cpdfkit-0.1.6.dist-info/top_level.txt
cpdfkit-0.1.6.dist-info/RECORD
