Metadata-Version: 2.1
Name: cpdfkit
Version: 0.1.6
Summary: A toolkit for rendering HTML to PDF using Chrome headless.
Home-page: https://github.com/codingcowde/cpdfkit
Author: Uli Toll
Author-email: cpdfkit@codingcow.de
License: UNKNOWN
Platform: UNKNOWN
Classifier: Development Status :: 3 - Alpha
Classifier: Intended Audience :: Developers
Classifier: License :: OSI Approved :: MIT License
Classifier: Programming Language :: Python :: 3
Classifier: Programming Language :: Python :: 3.6
Classifier: Programming Language :: Python :: 3.7
Classifier: Programming Language :: Python :: 3.8
Classifier: Programming Language :: Python :: 3.9
Classifier: Programming Language :: Python :: 3.10
Classifier: Operating System :: OS Independent
Requires-Python: >=3.6
License-File: LICENSE
